eight_puzzle_search/__init__.py
eight_puzzle_search-0.0.71.dist-info/LICENSE
eight_puzzle_search-0.0.71.dist-info/METADATA
eight_puzzle_search-0.0.71.dist-info/WHEEL
eight_puzzle_search-0.0.71.dist-info/top_level.txt
eight_puzzle_search-0.0.71.dist-info/RECORD
